eosjs_python/Exceptions.py
eosjs_python/__init__.py
eosjs_python/js/ActionDeserializer.js
eosjs_python/js/ContractDeserializer.js
eosjs_python/js/ConvertKey.js
eosjs_python/js/CreateAccount.js
eosjs_python/js/Decrypt.js
eosjs_python/js/Encrypt.js
eosjs_python/js/GenerateKeys.js
eosjs_python/js/GetAccount.js
eosjs_python/js/GetBlock.js
eosjs_python/js/GetCurrencyBalance.js
eosjs_python/js/GetTable.js
eosjs_python/js/PushContractTransaction.js
eosjs_python/js/Test.js
eosjs_python/js/Test2.js
eosjs_python/js/test.js
eosjs_python-0.2.6.dist-info/DESCRIPTION.rst
eosjs_python-0.2.6.dist-info/METADATA
eosjs_python-0.2.6.dist-info/RECORD
eosjs_python-0.2.6.dist-info/WHEEL
eosjs_python-0.2.6.dist-info/metadata.json
eosjs_python-0.2.6.dist-info/top_level.txt
